tests/data/test_collate.py
tests/data/test_representations.py
tests/datasets/test_binary_classification_dataset.py
tests/datasets/test_camelyon16_dataset.py
tests/datasets/test_ctscan_dataset.py
tests/datasets/test_false_frequency_mil_dataset.py
tests/datasets/test_mc_standard_mil_dataset.py
tests/datasets/test_pandamil_dataset.py
tests/datasets/test_processed_mil_dataset.py
tests/datasets/test_rsna_mil_dataset.py
tests/datasets/test_sc_standard_mil_dataset.py
tests/datasets/test_toy_dataset.py
tests/datasets/test_wsi_dataset.py
tests/models/test_abmil.py
tests/models/test_camil.py
tests/models/test_clam.py
tests/models/test_deepgraphsurv.py
tests/models/test_dsmil.py
tests/models/test_dtfdmil.py
tests/models/test_gtp.py
tests/models/test_iibmil.py
tests/models/test_mil_model.py
tests/models/test_patch_gcn.py
tests/models/test_prob_smooth_abmil.py
tests/models/test_setmil.py
tests/models/test_sm_abmil.py
tests/models/test_sm_transformer_abmil.py
tests/models/test_transformer_abmil.py
tests/models/test_transformer_prob_smooth_abmil.py
tests/models/test_transmil.py
tests/nn/test_max_pool.py
tests/nn/test_mean_pool.py
tests/nn/test_nn_utils.py
tests/nn/test_relprop.py
tests/nn/test_sm.py
tests/nn/attention/test_attention_pool.py
tests/nn/attention/test_irpe_multihead_self_attention.py
tests/nn/attention/test_multihead_cross_attention.py
tests/nn/attention/test_multihead_self_attention.py
tests/nn/attention/test_nystrom_attention.py
tests/nn/attention/test_prob_smooth_attention_pool.py
tests/nn/attention/test_sm_attention_pool.py
tests/nn/gnns/test_chebconv.py
tests/nn/gnns/test_deepgcn.py
tests/nn/gnns/test_dense_mincut_pool.py
tests/nn/gnns/test_gcn_conv.py
tests/nn/gnns/test_gnn_identity.py
tests/nn/transformers/test_conventional_transformer.py
tests/nn/transformers/test_encoder.py
tests/nn/transformers/test_irpe_transformer.py
tests/nn/transformers/test_layer.py
tests/nn/transformers/test_nystrom_transformer.py
tests/nn/transformers/test_sm_transformer.py
torchmil-1.0.0.dist-info/licenses/LICENSE
torchmil-1.0.0.dist-info/METADATA
torchmil-1.0.0.dist-info/WHEEL
torchmil-1.0.0.dist-info/top_level.txt
torchmil-1.0.0.dist-info/RECORD
