Metadata-Version: 2.4
Name: torchmil
Version: 1.0.0
Summary: Deep Multiple Instance Learning library for Pytorch
Author-email: Francisco Miguel Castro-Macías <francastro8b@gmail.com>
License-Expression: Apache-2.0
Project-URL: documentation, https://franblueee.github.io/torchmil/api/
Project-URL: homepage, https://franblueee.github.io/torchmil/
Project-URL: issues, https://github.com/Franblueee/torchmil/issues
Project-URL: repository, https://github.com/Franblueee/torchmil
Keywords: deep-learning,pytorch,multiple-instance-learning,multi-instance-learning,mil
Classifier: Intended Audience :: Developers
Classifier: Intended Audience :: Information Technology
Classifier: Intended Audience :: Science/Research
Classifier: Natural Language :: English
Classifier: Programming Language :: Python :: 3
Classifier: Topic :: Scientific/Engineering :: Artificial Intelligence
Classifier: Topic :: Scientific/Engineering :: Information Analysis
Classifier: Topic :: Scientific/Engineering :: Mathematics
Requires-Python: >=3.10
License-File: LICENSE
Requires-Dist: torch
Requires-Dist: tensordict
Requires-Dist: torchmetrics
Requires-Dist: einops
Requires-Dist: scipy
Requires-Dist: tqdm
Requires-Dist: numpy
Provides-Extra: dev
Requires-Dist: pre-commit; extra == "dev"
Requires-Dist: ruff; extra == "dev"
Requires-Dist: toml-sort; extra == "dev"
Provides-Extra: docs
Requires-Dist: mkdocs; extra == "docs"
Requires-Dist: mkdocs-material; extra == "docs"
Requires-Dist: mknotebooks; extra == "docs"
Requires-Dist: mkdocstrings; extra == "docs"
Requires-Dist: mkdocstrings-python; extra == "docs"
Requires-Dist: mkdocs-exclude; extra == "docs"
Provides-Extra: tests
Requires-Dist: torch; extra == "tests"
Requires-Dist: tensordict; extra == "tests"
Requires-Dist: torchmetrics; extra == "tests"
Requires-Dist: einops; extra == "tests"
Requires-Dist: scipy; extra == "tests"
Requires-Dist: tqdm; extra == "tests"
Requires-Dist: numpy; extra == "tests"
Requires-Dist: pytest; extra == "tests"
Requires-Dist: pytest-cov; extra == "tests"
Requires-Dist: pandas; extra == "tests"
Dynamic: license-file
